bangumi_parser/__init__.py
bangumi_parser/cli.py
bangumi_parser/config.py
bangumi_parser/core.py
bangumi_parser/utils.py
bangumi_parser-1.0.5.dist-info/METADATA
bangumi_parser-1.0.5.dist-info/WHEEL
bangumi_parser-1.0.5.dist-info/entry_points.txt
bangumi_parser-1.0.5.dist-info/licenses/LICENSE
bangumi_parser-1.0.5.dist-info/RECORD
