Metadata-Version: 2.4
Name: bangumi-parser
Version: 1.0.5
Summary: A library for parsing and organizing anime video files
Project-URL: Homepage, https://github.com/easybangumiorg/bangumi-parser
Project-URL: Repository, https://github.com/easybangumiorg/bangumi-parser
Project-URL: Issues, https://github.com/easybangumiorg/bangumi-parser/issues
Project-URL: Documentation, https://github.com/easybangumiorg/bangumi-parser#readme
Author-email: AyalaKaguya <support@easybangumi.org>
License: MIT
License-File: LICENSE
Keywords: anime,bangumi,media,organization,parser,video
Classifier: Development Status :: 4 - Beta
Classifier: Intended Audience :: Developers
Classifier: License :: OSI Approved :: MIT License
Classifier: Operating System :: OS Independent
Classifier: Programming Language :: Python :: 3
Classifier: Programming Language :: Python :: 3.10
Classifier: Programming Language :: Python :: 3.11
Classifier: Programming Language :: Python :: 3.12
Classifier: Topic :: Multimedia :: Video
Classifier: Topic :: Software Development :: Libraries :: Python Modules
Classifier: Topic :: Utilities
Requires-Python: >=3.10
Provides-Extra: dev
Requires-Dist: black>=23.0; extra == 'dev'
Requires-Dist: flake8>=6.0; extra == 'dev'
Requires-Dist: mypy>=1.0; extra == 'dev'
Requires-Dist: pytest-cov>=4.0; extra == 'dev'
Requires-Dist: pytest>=7.0; extra == 'dev'
Requires-Dist: twine>=4.0; extra == 'dev'
Provides-Extra: test
Requires-Dist: pytest-cov>=4.0; extra == 'test'
Requires-Dist: pytest>=7.0; extra == 'test'
